shimoku_api_python/__init__.py
shimoku_api_python/async_execution_pool.py
shimoku_api_python/base_resource.py
shimoku_api_python/client.py
shimoku_api_python/configuration.py
shimoku_api_python/exceptions.py
shimoku_api_python/execute_local_server.py
shimoku_api_python/execution_logger.py
shimoku_api_python/local_server.py
shimoku_api_python/schema_classes.py
shimoku_api_python/schema_parameter_classses.py
shimoku_api_python/utils.py
shimoku_api_python/websockets_server.py
shimoku_api_python/api/activity_metadata_api.py
shimoku_api_python/api/activity_template_metadata_api.py
shimoku_api_python/api/ai_api.py
shimoku_api_python/api/app_metadata_api.py
shimoku_api_python/api/business_metadata_api.py
shimoku_api_python/api/dashboard_metadata_api.py
shimoku_api_python/api/data_managing_api.py
shimoku_api_python/api/file_metadata_api.py
shimoku_api_python/api/ping_api.py
shimoku_api_python/api/plot_api.py
shimoku_api_python/api/report_metadata_api.py
shimoku_api_python/api/universe_metadata_api.py
shimoku_api_python/code_generation/file_generator.py
shimoku_api_python/code_generation/main_code_gen.py
shimoku_api_python/code_generation/tree_generation.py
shimoku_api_python/code_generation/utils_code_gen.py
shimoku_api_python/code_generation/business_code_gen/code_gen_from_business.py
shimoku_api_python/code_generation/business_code_gen/apps_code_gen/code_gen_from_apps.py
shimoku_api_python/code_generation/business_code_gen/apps_code_gen/data_sets_code_gen/code_gen_from_data_sets.py
shimoku_api_python/code_generation/business_code_gen/apps_code_gen/reports_code_gen/code_gen_from_reports.py
shimoku_api_python/code_generation/business_code_gen/apps_code_gen/reports_code_gen/report_types_code_gen/code_gen_from_annotated_echart.py
shimoku_api_python/code_generation/business_code_gen/apps_code_gen/reports_code_gen/report_types_code_gen/code_gen_from_button.py
shimoku_api_python-1.6.1.dist-info/LICENSE.txt
shimoku_api_python-1.6.1.dist-info/METADATA
shimoku_api_python-1.6.1.dist-info/WHEEL
shimoku_api_python-1.6.1.dist-info/top_level.txt
shimoku_api_python-1.6.1.dist-info/RECORD
